retinotopic_mapping/DisplayLogAnalysis.py
retinotopic_mapping/DisplayStimulus.py
retinotopic_mapping/MonitorSetup.py
retinotopic_mapping/RetinotopicMapping.py
retinotopic_mapping/StimulusRoutines.py
retinotopic_mapping/__init__.py
retinotopic_mapping/examples/signmap_analysis/example_altitude_map.tif
retinotopic_mapping/examples/signmap_analysis/example_altitude_power_map.tif
retinotopic_mapping/examples/signmap_analysis/example_azimuth_map.tif
retinotopic_mapping/examples/signmap_analysis/example_azimuth_power_map.tif
retinotopic_mapping/examples/signmap_analysis/example_vasculature_map.tif
retinotopic_mapping/examples/signmap_analysis/retinotopic_mapping_example.ipynb
retinotopic_mapping/examples/signmap_analysis/.ipynb_checkpoints/retinotopic_mapping_example-checkpoint.ipynb
retinotopic_mapping/examples/signmap_analysis/scripts/script_analysis.py
retinotopic_mapping/examples/signmap_analysis/scripts/script_mark_patches.py
retinotopic_mapping/examples/signmap_analysis/scripts/script_plot_patches.py
retinotopic_mapping/examples/visual_stimlation/example_combined_stimuli_comprehensive.py
retinotopic_mapping/examples/visual_stimlation/example_combined_stimuli_minimum.py
retinotopic_mapping/examples/visual_stimlation/example_drifting_grating_circle.py
retinotopic_mapping/examples/visual_stimlation/example_locally_sparse_noise.py
retinotopic_mapping/examples/visual_stimlation/example_minimum.py
retinotopic_mapping/other_test/io_test/co_test.py
retinotopic_mapping/other_test/io_test/device_test.py
retinotopic_mapping/other_test/io_test/di_test.py
retinotopic_mapping/other_test/io_test/do_line_selection.py
retinotopic_mapping/other_test/io_test/do_test.py
retinotopic_mapping/other_test/io_test/fake_encoder.py
retinotopic_mapping/other_test/io_test/system_test.py
retinotopic_mapping/other_test/io_test/task_test.py
retinotopic_mapping/other_test/timing_test/timing_tests.py
retinotopic_mapping/test/test_DisplayLogAnalysis.py
retinotopic_mapping-2.7.0.dist-info/DESCRIPTION.rst
retinotopic_mapping-2.7.0.dist-info/METADATA
retinotopic_mapping-2.7.0.dist-info/RECORD
retinotopic_mapping-2.7.0.dist-info/WHEEL
retinotopic_mapping-2.7.0.dist-info/metadata.json
retinotopic_mapping-2.7.0.dist-info/top_level.txt
