Metadata-Version: 2.0
Name: retinotopic-mapping
Version: 2.7.0
Summary: retinotopic mapping tools
Home-page: https://github.com/zhuangjun1981/retinotopic_mapping
Author: Jun Zhuang @ Allen Institute for Brain Science
Author-email: junz@alleninstitute.org
License: UNKNOWN
Platform: any
Classifier: Programming Language :: Python
Classifier: Development Status :: 4 - Beta
Classifier: Natural Language :: English
Classifier: Operating System :: OS Independent
Requires-Dist: tifffile (==0.10.0)
Requires-Dist: numpydoc (>=0.7.0)
Requires-Dist: sphinx (>=1.6.3)
Requires-Dist: psychopy (>=1.85.2)
Requires-Dist: PyDAQmx (>=1.3.2)
Requires-Dist: pyglet (==1.2.4)
Requires-Dist: configobj (>=5.0.6)
Requires-Dist: opencv-python (>=3.1.0)
Requires-Dist: pillow
Requires-Dist: h5py
Requires-Dist: scikit-image
Requires-Dist: matplotlib
Requires-Dist: scipy
Requires-Dist: numpy
Requires-Dist: pytest
